pydantic_init/__init__.py
pydantic_init/from_init.py
pydantic_init/instantiate.py
pydantic_init-0.1.0.dist-info/LICENSE
pydantic_init-0.1.0.dist-info/METADATA
pydantic_init-0.1.0.dist-info/WHEEL
pydantic_init-0.1.0.dist-info/RECORD
